feast_trino/__init__.py
feast_trino/feast_tests.py
feast_trino/trino.py
feast_trino/trino_source.py
feast_trino/trino_type_map.py
feast_trino/trino_utils.py
feast_trino-1.0.1.dist-info/LICENSE.md
feast_trino-1.0.1.dist-info/METADATA
feast_trino-1.0.1.dist-info/WHEEL
feast_trino-1.0.1.dist-info/top_level.txt
feast_trino-1.0.1.dist-info/RECORD
