Metadata-Version: 2.1
Name: feast-trino
Version: 1.0.1
Summary: Trino support for Feast offline store
Home-page: https://github.com/Shopify/feast-trino
Author: Shopify
Author-email: developers@shopify.com
License: MIT License
Project-URL: Bug Tracker, https://github.com/Shopify/feast-trino/issues
Keywords: feast featurestore trino offlinestore
Platform: UNKNOWN
Classifier: Development Status :: 2 - Pre-Alpha
Classifier: License :: OSI Approved :: MIT License
Classifier: Intended Audience :: Developers
Classifier: Programming Language :: Python
Classifier: Programming Language :: Python :: 3
Classifier: Programming Language :: Python :: 3.7
Classifier: Programming Language :: Python :: 3.8
Classifier: Programming Language :: Python :: 3.9
Classifier: Topic :: Software Development
Classifier: Topic :: Software Development :: Libraries
Classifier: Topic :: Software Development :: Libraries :: Python Modules
Requires-Python: >=3.7.0
License-File: LICENSE.md
Requires-Dist: feast (<1.0.0,>=0.15.0)
Requires-Dist: trino (<0.400.0,>=0.305.0)
Provides-Extra: ci
Requires-Dist: pytest (==6.0.0) ; extra == 'ci'
Requires-Dist: flake8 ; extra == 'ci'
Requires-Dist: black (==19.10b0) ; extra == 'ci'
Requires-Dist: isort (>=5) ; extra == 'ci'
Requires-Dist: mypy (==0.790) ; extra == 'ci'
